MANIFEST.in
README.md
pyproject.toml
setup.py
lisabeta/__init__.py
lisabeta/constants.h
lisabeta/pyconstants.c
lisabeta/pyconstants.pxd
lisabeta/pyconstants.pyx
lisabeta.egg-info/PKG-INFO
lisabeta.egg-info/SOURCES.txt
lisabeta.egg-info/dependency_links.txt
lisabeta.egg-info/top_level.txt
lisabeta/inference/__init__.py
lisabeta/inference/inference.py
lisabeta/inference/multiemcee.py
lisabeta/inference/multiemcee_smbh.py
lisabeta/inference/ptemcee_smbh.py
lisabeta/inference/ptemcee_sobh.py
lisabeta/inference/ptemcee_sobh_agn.py
lisabeta/inference/pymultinest_lvk.py
lisabeta/inference/pymultinest_multiband.py
lisabeta/inference/pymultinest_smbh.py
lisabeta/inference/pymultinest_sobh.py
lisabeta/lisa/LISAgeometry.c
lisabeta/lisa/LISAgeometry.h
lisabeta/lisa/LISAnoise.c
lisabeta/lisa/LISAnoise.h
lisabeta/lisa/LISAresponse.c
lisabeta/lisa/LISAresponse.h
lisabeta/lisa/__init__.py
lisabeta/lisa/ldcnoise.py
lisabeta/lisa/ldctools.py
lisabeta/lisa/lisa.py
lisabeta/lisa/lisa_fisher.py
lisabeta/lisa/lisatools.py
lisabeta/lisa/pyLISAnoise.c
lisabeta/lisa/pyLISAnoise.pxd
lisabeta/lisa/pyLISAnoise.pyx
lisabeta/lisa/pyresponse.c
lisabeta/lisa/pyresponse.pxd
lisabeta/lisa/pyresponse.pyx
lisabeta/lisa/snrtools.py
lisabeta/struct/__init__.py
lisabeta/struct/pystruct.c
lisabeta/struct/pystruct.pxd
lisabeta/struct/pystruct.pyx
lisabeta/struct/struct.c
lisabeta/struct/struct.h
lisabeta/tools/__init__.py
lisabeta/tools/fresnel.c
lisabeta/tools/fresnel.h
lisabeta/tools/overlap.c
lisabeta/tools/overlap.h
lisabeta/tools/pyoverlap.c
lisabeta/tools/pyoverlap.pxd
lisabeta/tools/pyoverlap.pyx
lisabeta/tools/pyspline.c
lisabeta/tools/pyspline.pxd
lisabeta/tools/pyspline.pyx
lisabeta/tools/pytools.c
lisabeta/tools/pytools.pxd
lisabeta/tools/pytools.pyx
lisabeta/tools/referenceframes.c
lisabeta/tools/referenceframes.h
lisabeta/tools/spline.c
lisabeta/tools/spline.h
lisabeta/tools/tools.c
lisabeta/tools/tools.h
lisabeta/utils/__init__.py
lisabeta/utils/corner_covar.py
lisabeta/utils/plotutils.py
lisabeta/waveforms/__init__.py
lisabeta/waveforms/bbh/EOBNRv2HMROM.c
lisabeta/waveforms/bbh/EOBNRv2HMROM.h
