Metadata-Version: 2.1
Name: lisabeta
Version: 1.0.2
Summary: Library to analyze gravitational-wave signals in LISA and LIGO-type detectors.
Author: Sylvain Marsat and John Baker and ...
Author-email: Sylvain Marsat <sylvain.marsat@l2it.in2p3.fr>, John Baker <john.g.baker@nasa.gov>
